{ "page":"1",
  "total":"5",
  "records":"5",
  "rows": [
	 { 
		"aprov" : "CENTRALIZADO",	 
	 	"referencia" : "317065",
	   "denominacion"    : "CJ CASTAÑA GRANEL",
	   "fecinicio"  : "29/04/2013",
	   "cantidad1" : "",
	   "fecha2" : "30/04/2013",
	   "cantidad2" : "",
 	   "fecha3" : "02/05/2013",
	   "cantidad3" : "",
	   "fecfin"  : "05/05/2013",	   
	   "uc"   : "6",
	   "estado" : "0"
	 },{ "aprov" : "CENTRALIZADO",
	   "referencia" : "2680776",
	   "denominacion"    : "CJ CASTAÑA GRANEL",
	   "fecinicio"  : "29/04/2013",
	   "cantidad1" : "",
	   "fecha2" : "30/04/2013",
	   "cantidad2" : "",
	   "fecha3" : "02/05/2013",
	   "cantidad3" : "",
	   "fecfin"  : "05/05/2013",	   
	   "uc"   : "6",
	   "estado" : "0"
	 },{"aprov" : "CENTRALIZADO",
	   "referencia" : "2680777",
	   "denominacion"    : "CJ CASTAÑA GRANEL",
	   "fecinicio"  : "29/04/2013",
	   "cantidad1" : "",
	   "fecha2" : "30/04/2013",
	   "cantidad2" : "",
	   "fecha3" : "02/05/2013",
	   "cantidad3" : "",
	   "fecfin"  : "05/05/2013",	   
	   "uc"   : "6",
	   "estado" : "1"
	 },{"aprov" : "CENTRALIZADO",
	   "referencia" : "2680778",
	   "denominacion"    : "CJ CASTAÑA GRANEL",
	   "fecinicio"  : "29/04/2013",
	   "cantidad1" : "6,00",
	   "fecha2" : "30/04/2013",
	   "cantidad2" : "6,00",
	   "fecha3" : "02/05/2013",
	   "cantidad3" : "6,00",
	   "fecfin"  : "05/05/2013",	   
	   "uc"   : "6",
	   "estado" : ""
	 },{"aprov" : "CENTRALIZADO",
	   "referencia" : "2680779",
	   "denominacion"    : "CJ CASTAÑA GRANEL",
	   "fecinicio"  : "29/04/2013",
	   "cantidad1" : "",
	   "fecha2" : "30/04/2013",
	   "cantidad2" : "",
	   "fecha3" : "02/05/2013",
	   "cantidad3" : "",
	   "fecfin"  : "05/05/2013",	   
	   "uc"   : "6",
	   "estado" : ""
	 }	 
   ]
}