{
  "rows": [
    {
      "ident": "14",
      "seccionGrid": "10-PESCADO MENUDO",
      "referencia": "976022",
      "descripcion": "CJ ANCHOA ENVASADO",
      "unidadesCaja": "6",
      "pdteRecibirManana": "0",
      "tirado": "5",
      "totImporteVentasEspejo": "3000",
      "previsionVenta": "2",
      "propuestaPedido": "9",
      "empuje": "S",
      "ofertaAB": "",
      "ofertaCD": "",
      "pvp": "8.5",
      "margen": "0",
      "tipoGama": "Obligatorio",
      "estado": "P"
    },
    {
      "ident": "15",
      "seccionGrid": "10-PESCADO MENUDO",
      "referencia": "225318",
      "descripcion": "CJ ANCHOA PEQUEÑA",
      "unidadesCaja": "7",
      "pdteRecibirManana": "0",
      "tirado": "5",
      "totImporteVentasEspejo": "3000",
      "previsionVenta": "8",
      "propuestaPedido": "1",
      "empuje": "S",
      "ofertaAB": "",
      "ofertaCD": "",
      "pvp": "7.95",
      "margen": "0",
      "tipoGama": "Obligatorio",
      "estado": "P"
    },
    {
      "ident": "16",
      "seccionGrid": "10-PESCADO MENUDO",
      "referencia": "1687847",
      "descripcion": "CJ ANCHOA PEQUEÑA ENVASADO",
      "unidadesCaja": "7",
      "pdteRecibirManana": "0",
      "tirado": "5",
      "totImporteVentasEspejo": "3000",
      "previsionVenta": "8",
      "propuestaPedido": "1",
      "empuje": "S",
      "ofertaAB": "",
      "ofertaCD": "",
      "pvp": "7.95",
      "margen": "0",
      "tipoGama": "Obligatorio",
      "estado": "P"
    }
  ]
}