{
	"p42PedidoAdicionalMColNames" : [ 
		"Estado",
		"Desc. Oferta",
		"ID Vegalsa",
		"Referencia",
		"Agrupación",
		"Denominación",
		"F. Inicio",
		"F. Fin",
		"Impl. Inicial",
		"Impl. final",
		"Cantid. 1",
		"Cantid. 2",
		"Cantid. 3",
		"Cantid. 4",
		"Cantid. 5",
		"U/C",
		"Excl",
		"Cant. Min",
		"Cant. Max",
		"Color",
		"Talla",
		"Modelo Proveedor"
	],
	
	
	"p42PedidoAdicionalMGridTitle" : "Montaje adicional",
	"emptyRecords" : "No hay registros",
	"emptyListaSeleccionados" : "No hay registros seleccionados",
	"iconoModificado" : "Modificado",
	"errorModificacion" : "Se ha producido un error de WS en la modificación del pedido",
	"errorModificacionFechas" : "Para la modificación se deben seleccionar pedidos con la misma fecha fin",
	"errorModificacionValFecInicio" : "Se ha producido un error en el WS de validación al obtener la fecha de inicio del pedido",
	"errorModificacionNoModif" : "El pedido seleccionado no es modificable",
	"errorModificacionNoMasiva" : "Error no existen modificaciones masivas",
	"errorBorrado" : "Se ha producido un error de WS en el borrado del pedido",
	"errorBorradoNoBorrable" : "Referencia no se puede borrar al estar bloqueada",
	"tableFilter":"Filtrado de columnas",
	"noRecordsToExport" : "No hay registros",
	"codArticuloTitle":"Referencia",
	"descriptionArtTitle":"Denominación",
	"codArticuloGridTitle":"Referencia",
	"descriptionArtGridTitle":"Denominación",
	"fechaInicioTitle":"Fecha Inicio",
	"fechaFinTitle":"Fecha Fin",
	"capMaxTitle":"Implantación Inicial",
	"capMinTitle":"Implantación Final",
	"cantidad1Title":"Cantidad 1",
	"cantidad2Title":"Cantidad 2",
	"cantidad3Title":"Cantidad 3",
	"uniCajaServTitle":"Unidades Caja",
	"excluirTitle":"Excluir",
	"cantMaxTitle":"Cantidad máxima",
	"cantMinTitle":"Cantidad mínima",
	"descOfertaTitle":"Descripción oferta",
	"mensajeTitle":"Estado",
	"colorTitle":"Color",
	"tallaTitle":"Talla",
	"modeloProveedorTitle":"Modelo Proveedor",
	"tipoMontaje":"MONTAJE ADICIONAL",
	"sinOferta":"SIN OFERTA/9203",
	"textoFechaInicio":"Fecha Inicio",
	"textoImplInicial":"Impl.Inicial",
	"textoImplFinal":"Impl.Final",
	"p42ComboSI" : "SI",
	"p42ComboNO" : "NO",
	"p42BotonGuardar" : "Guardar",
	"p42BotonVolver" : "Volver",
	"p42EstadoNoActiva" : "BLOQUEADA",
	"p42EstadoBloqueada" : "BLOQUEADA",
	"p42ConsultaMotivosBloqueo": "Consulta motivos de bloqueo",
	"p42CmbOfertaTodos": " ",
	"p42CmbPromocionTodos": " "
}